setup.cfg
setup.py
ofxutils/__init__.py
ofxutils/enumerator.py
ofxutils/ofxtools.py
ofxutils.egg-info/PKG-INFO
ofxutils.egg-info/SOURCES.txt
ofxutils.egg-info/dependency_links.txt
ofxutils.egg-info/requires.txt
ofxutils.egg-info/top_level.txt