Metadata-Version: 1.1
Name: ofxutils
Version: 1.0
Summary: Provide tools for financial file parsing and conversion.
Home-page: http://github.com/afer92/ofxutils
Author: afer92
Author-email: ferraro.alain@free.fr
License: GNU General Public License (GPL)
Keywords: ofx ofc qif utilities
Platform: UNKNOWN
Classifier: Development Status :: 4 - Beta
Classifier: License :: OSI Approved :: GNU General Public License (GPL)
Classifier: Programming Language :: Python :: 3
Classifier: Programming Language :: Python :: 3.4
